fsttest/__init__.py
fsttest/__main__.py
fsttest/__version__.py
fsttest/_fst.py
fsttest/_results.py
fsttest/_run.py
fsttest/_test_case.py
fsttest/exceptions.py
fsttest-0.5.0.dist-info/entry_points.txt
fsttest-0.5.0.dist-info/LICENSE
fsttest-0.5.0.dist-info/WHEEL
fsttest-0.5.0.dist-info/METADATA
fsttest-0.5.0.dist-info/RECORD
