Metadata-Version: 2.1
Name: fsttest
Version: 0.5.0
Summary: Test Foma FSTs
Home-page: https://github.com/eddieantonio/fsttest
License: MPL-2.0
Author: Eddie Antoio Santos
Author-email: Eddie.Santos@nrc-cnrc.gc.ca
Requires-Python: >=3.6,<4.0
Classifier: License :: OSI Approved
Classifier: Programming Language :: Python :: 3
Classifier: Programming Language :: Python :: 3.6
Classifier: Programming Language :: Python :: 3.7
Classifier: Programming Language :: Python :: 3.8
Requires-Dist: blessings (>=1.7,<2.0)
Requires-Dist: toml (>=0.10.0,<0.11.0)
Project-URL: Repository, https://github.com/eddieantonio/fsttest.git
